heare/__init__.py
heare/_version.py
heare/developer/__init__.py
heare/developer/agent.py
heare/developer/cli.py
heare/developer/commit.py
heare/developer/compacter.py
heare/developer/context.py
heare/developer/hdev.py
heare/developer/history.py
heare/developer/issues_cli.py
heare/developer/memory.py
heare/developer/models.py
heare/developer/prompt.py
heare/developer/rate_limiter.py
heare/developer/sandbox.py
heare/developer/toolbox.py
heare/developer/user_interface.py
heare/developer/utils.py
heare/developer/clients/__init__.py
heare/developer/clients/plane_cache.py
heare/developer/clients/plane_so.py
heare/developer/personas/__init__.py
heare/developer/personas/basic_agent.py
heare/developer/personas/coding_agent.py
heare/developer/personas/deep_research_agent.py
heare/developer/tools/__init__.py
heare/developer/tools/files.py
heare/developer/tools/framework.py
heare/developer/tools/gcal.py
heare/developer/tools/github.py
heare/developer/tools/github_comments.py
heare/developer/tools/gmail.py
heare/developer/tools/google_auth_cli.py
heare/developer/tools/google_shared.py
heare/developer/tools/issues.py
heare/developer/tools/memory.py
heare/developer/tools/repl.py
heare/developer/tools/sessions.py
heare/developer/tools/shell.py
heare/developer/tools/subagent.py
heare/developer/tools/tmux_session.py
heare/developer/tools/tmux_tool.py
heare/developer/tools/todos.py
heare/developer/tools/web.py
heare/developer/web/__init__.py
heare/developer/web/app.py
heare/developer/web/static/style.css
heare/developer/web/templates/base.html
heare/developer/web/templates/directory.html
heare/developer/web/templates/entry.html
heare/developer/web/templates/error.html
heare/developer/web/templates/search.html
heare/developer/web/templates/tree.html
heare_developer-0.9.11.dist-info/METADATA
heare_developer-0.9.11.dist-info/WHEEL
heare_developer-0.9.11.dist-info/entry_points.txt
heare_developer-0.9.11.dist-info/top_level.txt
heare_developer-0.9.11.dist-info/RECORD
