Metadata-Version: 2.4
Name: heare-developer
Version: 0.9.11
Summary: A command-line agent.
Author-email: Sean Fitzgerald <sean@fitzgeralds.me>
Classifier: Programming Language :: Python :: 3
Classifier: License :: OSI Approved :: MIT License
Classifier: Operating System :: OS Independent
Requires-Python: >=3.11
Requires-Dist: anthropic==0.42.0
Requires-Dist: python-dotenv==1.0.1
Requires-Dist: pathspec==0.12.1
Requires-Dist: prompt_toolkit==3.0.47
Requires-Dist: rich==13.7.1
Requires-Dist: brave-search-python-client>=0.4.27
Requires-Dist: beautifulsoup4>=4.13.3
Requires-Dist: markdownify>=1.0.0
Requires-Dist: google-api-python-client>=2.166.0
Requires-Dist: google-auth-oauthlib>=1.2.1
Requires-Dist: pyyaml>=6.0.2
Requires-Dist: flask>=3.1.0
Requires-Dist: markdown>=3.8
Requires-Dist: psutil>=7.0.0
Requires-Dist: pytz>=2025.2
Requires-Dist: aiofiles>=24.1.0
Requires-Dist: httpx>=0.27.0
